[
 {
  "id": 1,
  "name": "buzo nike blanco",
  "description": "libero ut massa volutpat convallis morbi odio odio elementum eu interdum eu tincidunt in leo maecenas pulvinar lobortis est phasellus sit amet erat nulla tempus vivamus in felis eu sapien cursus vestibulum proin eu mi",
  "price": 3144,
  "discount": 25,
  "category": "in-sale",
  "image": "oferta1.jpg"
 },
 {
  "id": 2,
  "name": "remera nike azul",
  "description": "fusce congue diam id ornare imperdiet sapien urna pretium nisl ut volutpat sapien arcu sed augue aliquam erat volutpat in congue etiam justo etiam pretium iaculis justo in hac habitasse platea dictumst etiam faucibus cursus urna ut tellus nulla ut erat id mauris vulputate elementum nullam",
  "price": 4163,
  "discount": 45,
  "category": "in-sale",
  "image": "oferta2.jpg"
 },
 {
  "id": 3,
  "name": "musculosa nike",
  "description": "justo in blandit ultrices enim lorem ipsum dolor sit amet consectetuer adipiscing elit proin interdum mauris non ligula pellentesque ultrices phasellus id sapien",
  "price": 3546,
  "discount": 38,
  "category": "in-sale",
  "image": "oferta3.jpg"
 },
 {
  "id": 4,
  "name": "buzo verde nike",
  "description": "nisl venenatis lacinia aenean sit amet justo morbi ut odio cras mi pede malesuada in imperdiet et commodo vulputate justo in blandit ultrices enim lorem ipsum dolor sit amet consectetuer adipiscing elit proin interdum mauris non ligula pellentesque",
  "price": 1178,
  "discount": 45,
  "category": "in-sale",
  "image": "oferta4.jpg"
 },
 {
  "id": 5,
  "name": "Buzo nike negro",
  "description": "lacus morbi sem mauris laoreet ut rhoncus aliquet pulvinar sed nisl nunc rhoncus dui vel sem sed sagittis nam congue risus semper porta volutpat quam pede lobortis ligula sit amet eleifend pede libero quis orci nullam molestie nibh in lectus pellentesque",
  "price": 1368,
  "discount": 35,
  "category": "in-sale",
  "image": "oferta6.jpg"
 },
 {
  "id": 6,
  "name": "short nike negro",
  "description": "molestie lorem quisque ut erat curabitur gravida nisi at nibh in hac habitasse platea dictumst aliquam augue quam sollicitudin vitae consectetuer eget rutrum at lorem integer tincidunt ante vel",
  "price": 4309,
  "discount": 29,
  "category": "in-sale",
  "image": "oferta7.jpg"
 },
 {
  "id": 7,
  "name": "zapatillas reebok",
  "price": "12",
  "discount": "12",
  "category": "in-sale",
  "description": "asasdasda",
  "image": "image-1654213671321.jpg"
 },
 {
  "id": 8,
  "name": "",
  "price": "1231",
  "discount": "12",
  "category": "in-sale",
  "description": "asadasda",
  "image": "image-1654230809102.jpg"
 },
 {
  "id": 9,
  "name": "",
  "price": "1231",
  "discount": "15",
  "category": "in-sale",
  "description": "asdasda",
  "image": "image-1654231087686.jpg"
 },
 {
  "id": 10,
  "name": "",
  "price": "",
  "discount": "123",
  "category": "in-sale",
  "description": "asdasdas",
  "image": "image-1654231231612.jpg"
 },
 {
  "id": 11,
  "name": "",
  "price": "",
  "discount": "",
  "category": "",
  "description": ""
 },
 {
  "id": 12,
  "name": "",
  "price": "",
  "discount": "",
  "category": "",
  "description": ""
 },
 {
  "id": 13,
  "name": "",
  "price": "",
  "discount": "",
  "category": "",
  "description": ""
 },
 {
  "id": 14,
  "name": "",
  "price": "",
  "discount": "",
  "category": "",
  "description": ""
 },
 {
  "id": 15,
  "name": "",
  "price": "",
  "discount": "",
  "category": "",
  "description": ""
 },
 {
  "id": 16,
  "name": "",
  "price": "",
  "discount": "",
  "category": "",
  "description": ""
 },
 {
  "id": 17,
  "name": "a",
  "price": "",
  "discount": "",
  "category": "",
  "description": ""
 }
]